cef_logger/__init__.py
cef_logger/event.py
cef_logger/event.pyi
cef_logger/fields.py
cef_logger/fields.pyi
cef_logger/schemas.py
cef_logger-1.0.0.dist-info/LICENSE
cef_logger-1.0.0.dist-info/WHEEL
cef_logger-1.0.0.dist-info/METADATA
cef_logger-1.0.0.dist-info/RECORD
