Metadata-Version: 2.1
Name: cef_logger
Version: 1.0.0
Summary: ArcEvent -- Class for creating events for logging.
Author-email: Alexander Morokov <morocov.ap.muz@gmail.com>
Requires-Python: >=3.6.0
Classifier: License :: OSI Approved :: MIT License
Classifier: Programming Language :: Python :: 3 :: Only
Classifier: Programming Language :: Python :: 3.6
Classifier: Programming Language :: Python :: 3.7
Classifier: Programming Language :: Python :: 3.8
Classifier: Programming Language :: Python :: 3.9
Classifier: Programming Language :: Python :: 3.10
Requires-Dist: pydantic >=1.6.1, <2.0.0
Requires-Dist: pytest >=5.4.3,<6.0.0 ; extra == "test"
Requires-Dist: flake8 >=3.9.2,<4.0.0 ; extra == "test"
Requires-Dist: flake8-bugbear >=0.11.1,<0.12.0 ; extra == "test"
Requires-Dist: flake8-builtins >=1.5.3,<2.0.0 ; extra == "test"
Requires-Dist: flake8-comprehensions >=3.7.0,<4.0.0 ; extra == "test"
Requires-Dist: flake8-debugger >=3.2.1,<4.0.0 ; extra == "test"
Requires-Dist: flake8-isort >=3.0.1,<4.0.0 ; extra == "test"
Requires-Dist: flake8-logging-format >=0.6.0,<0.7.0 ; extra == "test"
Requires-Dist: flake8-mutable >=1.2.0,<2.0.0 ; extra == "test"
Requires-Dist: flake8-pep3101 >=1.3.0,<2.0.0 ; extra == "test"
Requires-Dist: flake8-print >=3.1.4,<4.0.0 ; extra == "test"
Requires-Dist: flake8-quotes >=3.3.1,<4.0.0 ; extra == "test"
Requires-Dist: flake8-string-format >=0.3.0,<0.4.0 ; extra == "test"
Requires-Dist: mypy >=0.910,<1.0 ; extra == "test"
Requires-Dist: isort >=4.3.21,<5.0.0 ; extra == "test"
Project-URL: Home, https://github.com/delatars/cef_logger
Provides-Extra: test
